flame_hub/__init__.py
flame_hub/_auth_client.py
flame_hub/_auth_flows.py
flame_hub/_base_client.py
flame_hub/_core_client.py
flame_hub/_defaults.py
flame_hub/_exceptions.py
flame_hub/_storage_client.py
flame_hub/_version.py
flame_hub/auth.py
flame_hub/models.py
flame_hub/types.py
flame_hub_client-0.2.9.dist-info/LICENSE
flame_hub_client-0.2.9.dist-info/METADATA
flame_hub_client-0.2.9.dist-info/WHEEL
flame_hub_client-0.2.9.dist-info/RECORD
