Metadata-Version: 2.3
Name: flame-hub-client
Version: 0.2.9
Summary: HTTP client for interacting with FLAME Hub services.
License: Apache-2.0
Author: Maximilian Jugl
Author-email: Maximilian.Jugl@medizin.uni-leipzig.de
Requires-Python: >=3.10,<4
Classifier: Development Status :: 4 - Beta
Requires-Dist: httpcore (>=1.0.9,<2.0.0)
Requires-Dist: httpx (>=0.28.0,<0.29.0)
Requires-Dist: pydantic (>=2.10.0,<3.0.0)
Project-URL: Documentation, https://privateaim.github.io/hub-python-client/
Project-URL: Homepage, https://privateaim.de/
Project-URL: Repository, https://github.com/PrivateAIM/hub-python-client/
